Metadata-Version: 1.1
Name: vectoria
Version: 0.0.5
Summary: Vectoria A Word Vector Encoder, used to turn word strings into dense numerical embeddings for machine learning models.
Home-page: https://github.com/wballard/vectoria
Author: Will Ballard
Author-email: wballard@mailframe.net
License: BSD 3-Clause License
Platform: UNKNOWN
Classifier: Intended Audience :: Developers
Classifier: Intended Audience :: Science/Research
Classifier: License :: OSI Approved :: BSD License
Classifier: Programming Language :: Python :: 3.4
Classifier: Programming Language :: Python :: 3.5
Classifier: Topic :: Scientific/Engineering :: Artificial Intelligence
